zidfs/__init__.py
zidfs/zidfsouno.py
zidfsouno-0.1.3.dist-info/licenses/LICENSE
zidfsouno-0.1.3.dist-info/METADATA
zidfsouno-0.1.3.dist-info/WHEEL
zidfsouno-0.1.3.dist-info/top_level.txt
zidfsouno-0.1.3.dist-info/RECORD
