Metadata-Version: 2.4
Name: zidfsouno
Version: 0.1.3
Summary: 工具包
Author: ouhuahu
Author-email: 362654377@qq.com
License: MIT
Requires-Python: >=3.10
License-File: LICENSE
Requires-Dist: pandas
Dynamic: author
Dynamic: author-email
Dynamic: description-content-type
Dynamic: license
Dynamic: license-file
Dynamic: requires-dist
Dynamic: requires-python
Dynamic: summary
